pyvorse/__init__.py
pyvorse/core/__init__.py
pyvorse/data/__init__.py
pyvorse/data/deep.py
pyvorse/data/positioned.py
pyvorse/data/simple.py
pyvorse/data/smart.py
pyvorse/data/spiders.py
pyvorse/data/table.py
pyvorse/mathematics/__init__.py
pyvorse/mathematics/helpful.py
pyvorse/pipeline/__init__.py
pyvorse/pipeline/datacell.py
pyvorse/pipeline/mains.py
pyvorse/pipeline/routers.py
pyvorse/randoms/__init__.py
pyvorse/randoms/selectors.py
pyvorse/randoms/statistics.py
pyvorse/tests/__init__.py
pyvorse/tests/exprs.py
pyvorse/tests/other.py
pyvorse-1.0.4.dist-info/WHEEL
pyvorse-1.0.4.dist-info/METADATA
pyvorse-1.0.4.dist-info/RECORD
