Metadata-Version: 2.1
Name: pyvorse
Version: 1.0.4
Summary: Simple essentials extension library of additions to vanilla python.
Home-page: https://github.com/Vladislav-Martian/pyverse
License: MIT
Keywords: essentials,extension,simple,small
Author: Vladislav-Martian
Author-email: me.as.martian@gmail.com
Requires-Python: >=3.9,<4.0
Classifier: License :: OSI Approved :: MIT License
Classifier: Programming Language :: Python :: 3
Classifier: Programming Language :: Python :: 3.9
Classifier: Topic :: Utilities
Project-URL: Documentation, https://github.com/Vladislav-Martian/pyverse/wiki
Project-URL: Repository, https://github.com/Vladislav-Martian/pyverse
